bitcoin_xyz/__init__.py
bitcoin_xyz-0.0.1.dist-info/LICENSE
bitcoin_xyz-0.0.1.dist-info/METADATA
bitcoin_xyz-0.0.1.dist-info/WHEEL
bitcoin_xyz-0.0.1.dist-info/top_level.txt
bitcoin_xyz-0.0.1.dist-info/RECORD
