Metadata-Version: 2.1
Name: bitcoin-xyz
Version: 0.0.1
Summary: This is a bitcoin tools package.
Home-page: https://github.com/sincatgit/bitcoin_xyz
Author: alphajon
Author-email: alphajon@126.com
License: UNKNOWN
Platform: UNKNOWN
Classifier: Programming Language :: Python :: 3
Classifier: License :: OSI Approved :: MIT License
Classifier: Operating System :: OS Independent
